vanguard/__init__.py
vanguard/account.py
vanguard/order.py
vanguard/session.py
vanguard/urls.py
vanguard_api-0.3.3.dist-info/licenses/LICENSE
vanguard_api-0.3.3.dist-info/METADATA
vanguard_api-0.3.3.dist-info/WHEEL
vanguard_api-0.3.3.dist-info/top_level.txt
vanguard_api-0.3.3.dist-info/RECORD
