Metadata-Version: 2.4
Name: vanguard-api
Version: 0.3.3
Summary: An unofficial API for Vanguard Invest
Home-page: https://github.com/MaxxRK/vanguard-api
Download-URL: https://github.com/MaxxRK/vanguard-api/archive/refs/tags/v0.3.3.tar.gz
Author: MaxxRK
Author-email: maxxrk@pm.me
License: MIT
Keywords: VANGUARD,API
Classifier: Development Status :: 3 - Alpha
Classifier: Intended Audience :: Developers
Classifier: Topic :: Internet :: WWW/HTTP :: Session
Classifier: License :: OSI Approved :: MIT License
Classifier: Programming Language :: Python :: 3
Classifier: Programming Language :: Python :: 3.8
Classifier: Programming Language :: Python :: 3.9
Classifier: Programming Language :: Python :: 3.10
Classifier: Programming Language :: Python :: 3.11
License-File: LICENSE
Requires-Dist: playwright
Requires-Dist: playwright-sm
Dynamic: author
Dynamic: author-email
Dynamic: classifier
Dynamic: description
Dynamic: description-content-type
Dynamic: download-url
Dynamic: home-page
Dynamic: keywords
Dynamic: license
Dynamic: license-file
Dynamic: requires-dist
Dynamic: summary
